#Command:
## use object
javap -c -l -classpath ./test_useobject-0.0.1.jar zxf.UseObject

## use string
javap -c -l -classpath ./test_usestring-0.0.1.jar zxf.UseString


#Result:
davis@davis-TM1703:~/Davis/zxf-java-compile/overloading/output$ # use object
davis@davis-TM1703:~/Davis/zxf-java-compile/overloading/output$ javap -c -l -classpath ./test_useobject-0.0.1.jar zxf.UseObject
Compiled from "UseObject.java"
public class zxf.UseObject {
  public zxf.UseObject();
    Code:
       0: aload_0
       1: invokespecial #1                  // Method java/lang/Object."<init>":()V
       4: return
    LineNumberTable:
      line 3: 0
    LocalVariableTable:
      Start  Length  Slot  Name   Signature
          0       5     0  this   Lzxf/UseObject;

  public static void main(java.lang.String[]);
    Code:
       0: getstatic     #2                  // Field java/lang/System.out:Ljava/io/PrintStream;
       3: new           #3                  // class java/lang/Object
       6: dup
       7: invokespecial #1                  // Method java/lang/Object."<init>":()V
      10: invokestatic  #4                  // Method zxf/OverLoading.staticOverloading:(Ljava/lang/Object;)Ljava/lang/String;
      13: invokevirtual #5                  // Method java/io/PrintStream.println:(Ljava/lang/String;)V
      16: getstatic     #2                  // Field java/lang/System.out:Ljava/io/PrintStream;
      19: new           #6                  // class zxf/OverLoading
      22: dup
      23: invokespecial #7                  // Method zxf/OverLoading."<init>":()V
      26: new           #3                  // class java/lang/Object
      29: dup
      30: invokespecial #1                  // Method java/lang/Object."<init>":()V
      33: invokevirtual #8                  // Method zxf/OverLoading.overloading:(Ljava/lang/Object;)Ljava/lang/String;
      36: invokevirtual #5                  // Method java/io/PrintStream.println:(Ljava/lang/String;)V
      39: return
    LineNumberTable:
      line 5: 0
      line 6: 16
      line 7: 39
    LocalVariableTable:
      Start  Length  Slot  Name   Signature
          0      40     0  args   [Ljava/lang/String;
}
davis@davis-TM1703:~/Davis/zxf-java-compile/overloading/output$
davis@davis-TM1703:~/Davis/zxf-java-compile/overloading/output$ # use string
davis@davis-TM1703:~/Davis/zxf-java-compile/overloading/output$ javap -c -l -classpath ./test_usestring-0.0.1.jar zxf.UseString
Compiled from "UseString.java"
public class zxf.UseString {
  public zxf.UseString();
    Code:
       0: aload_0
       1: invokespecial #1                  // Method java/lang/Object."<init>":()V
       4: return
    LineNumberTable:
      line 3: 0
    LocalVariableTable:
      Start  Length  Slot  Name   Signature
          0       5     0  this   Lzxf/UseString;

  public static void main(java.lang.String[]);
    Code:
       0: getstatic     #2                  // Field java/lang/System.out:Ljava/io/PrintStream;
       3: ldc           #3                  // String static string
       5: invokestatic  #4                  // Method zxf/OverLoading.staticOverloading:(Ljava/lang/String;)Ljava/lang/String;
       8: invokevirtual #5                  // Method java/io/PrintStream.println:(Ljava/lang/String;)V
      11: getstatic     #2                  // Field java/lang/System.out:Ljava/io/PrintStream;
      14: new           #6                  // class zxf/OverLoading
      17: dup
      18: invokespecial #7                  // Method zxf/OverLoading."<init>":()V
      21: ldc           #8                  // String string
      23: invokevirtual #9                  // Method zxf/OverLoading.overloading:(Ljava/lang/String;)Ljava/lang/String;
      26: invokevirtual #5                  // Method java/io/PrintStream.println:(Ljava/lang/String;)V
      29: return
    LineNumberTable:
      line 5: 0
      line 6: 11
      line 7: 29
    LocalVariableTable:
      Start  Length  Slot  Name   Signature
          0      30     0  args   [Ljava/lang/String;
}
